signmeup/__init__.py
signmeup/cli.py
signmeup/manage.py
signmeup/accounts/__init__.py
signmeup/accounts/admin.py
signmeup/accounts/apps.py
signmeup/accounts/middleware.py
signmeup/accounts/models.py
signmeup/accounts/serializers.py
signmeup/accounts/tests.py
signmeup/accounts/urls.py
signmeup/accounts/views.py
signmeup/accounts/migrations/0001_initial.py
signmeup/accounts/migrations/0002_customuser_email_verified_delete_user.py
signmeup/accounts/migrations/0003_userprofile.py
signmeup/accounts/migrations/0004_userprofile_avatar_userprofile_contact_number_and_more.py
signmeup/accounts/migrations/__init__.py
signmeup/core/__init__.py
signmeup/core/asgi.py
signmeup/core/settings.py
signmeup/core/urls.py
signmeup/core/wsgi.py
signmeup-0.0.3.dist-info/METADATA
signmeup-0.0.3.dist-info/WHEEL
signmeup-0.0.3.dist-info/entry_points.txt
signmeup-0.0.3.dist-info/top_level.txt
signmeup-0.0.3.dist-info/RECORD
